LICENSE
README.md
setup.py
codetoolkit/JavaAnalysis-1.0-SNAPSHOT.jar
codetoolkit/__init__.py
codetoolkit/action_parser.py
codetoolkit/call_graph_analyzer.py
codetoolkit/code2vec.py
codetoolkit/code_chunker.py
codetoolkit/code_cleaner.py
codetoolkit/code_pos.py
codetoolkit/code_stopwords.py
codetoolkit/code_tokenizer.py
codetoolkit/delimiter.py
codetoolkit/dependency_analyzer.py
codetoolkit/dictionary.py
codetoolkit/lemmatizer.py
codetoolkit/pair_checker.py
codetoolkit/predicates.txt
codetoolkit/verb.txt
codetoolkit/verb_helper.py
codetoolkit.egg-info/PKG-INFO
codetoolkit.egg-info/SOURCES.txt
codetoolkit.egg-info/dependency_links.txt
codetoolkit.egg-info/requires.txt
codetoolkit.egg-info/top_level.txt
codetoolkit/javalang/__init__.py
codetoolkit/javalang/ast.py
codetoolkit/javalang/javadoc.py
codetoolkit/javalang/parse.py
codetoolkit/javalang/parser.py
codetoolkit/javalang/tokenizer.py
codetoolkit/javalang/tree.py
codetoolkit/javalang/util.py
codetoolkit/posse/__init__.py
codetoolkit/posse/candidate_provider.py
codetoolkit/posse/chunker.py
codetoolkit/posse/resource.py
codetoolkit/posse/tagger.py
codetoolkit/posse/corpus/normal.fields
codetoolkit/posse/corpus/normal.methods
codetoolkit/posse/dicts/adjective
codetoolkit/posse/dicts/adverb
codetoolkit/posse/dicts/dictionary-allwords
codetoolkit/posse/dicts/dlist
codetoolkit/posse/dicts/irregV
codetoolkit/posse/dicts/n-abbr
codetoolkit/posse/dicts/norule
codetoolkit/posse/dicts/noun
codetoolkit/posse/dicts/participle
codetoolkit/posse/dicts/preposition
codetoolkit/posse/dicts/pronoun
codetoolkit/posse/dicts/quant
codetoolkit/posse/dicts/verb
codetoolkit/spiral/__init__.py
codetoolkit/spiral/__main__.py
codetoolkit/spiral/__version__.py
codetoolkit/spiral/constants.py
codetoolkit/spiral/frequencies.py
codetoolkit/spiral/ronin.py
codetoolkit/spiral/samurai.py
codetoolkit/spiral/simple_splitters.py
codetoolkit/spiral/utils.py
codetoolkit/spiral/data/README.md
codetoolkit/spiral/data/dictionary.pklz
codetoolkit/spiral/data/frequencies.pklz
test/test_abbr.py
test/test_cg.py
test/test_code2vec.py
test/test_code_pos.py
test/test_delimiter.py
test/test_dependence.py
test/test_javalang.py